{
  "_id": "cc4448af94b97ca266b76f63",
  "deviceId": "c339f6ce-fe26-4788-beee-c97605f50403",
  "category": "channel",
  "categories": ["Connected Car"],
  "description": "",
  "documentation": "https://developer.automatic.com/api-reference/",
  "helpText": "Automatic connects your car to the rest of your digital life. Get detailed information about trips in a drivers' timeline, save money on gas with valuable feedback, and even call for help in the case of a crash.",
  "enabled": true,
  "name": "Automatic",
  "skynet": {
    "type": "channel",
    "subtype": "Automatic"
  },
  "channelid": "a1374caca54610a9f1b64db5",
  "type": "channel:automatic"
}
