{
  "_id": "22ede53a-7e5d-42d5-84ac-fd5debe042f9",
  "category": "channel",
  "categories": ["Office"],
  "description": "Double Click Search",
  "documentation": "https://developers.google.com/doubleclick-search/v2/reference/",
  "helpText": "A management platform that helps agencies/ marketers efficiently create, manage, and track marketing campaigns across multiple search engines and media channels.",
  "enabled": true,
  "name": "Double Click Search",
  "skynet": {
    "type": "channel",
    "subtype": "doubleclicksearch"
  },
  "channelid": "40f9dd2f955243aa8dc20bd21d865fb3",
  "type": "channel:doubleclicksearch"
}
