{
  "_id": "54a449d8620f5ebb13dbc4f0",
  "deviceId": "c339f6ce-fe26-4788-beee-c97605f50403",
  "category": "channel",
  "categories": ["Citrix"],
  "description": "Right Signature",
  "documentation": "http://rightsignature.pbworks.com/w/page/8882240/FrontPage",
  "helpText": "The easiest, fastest way to get documents filled out and signed online. Get Document information, send out email reminders, update templates, and more.",
  "enabled": true,
  "name": "Right Signature",
  "skynet": {
    "type": "channel",
    "subtype": "rightsignature"
  },
  "channelid": "54a44e1f620f5ebb13dbc4f1",
  "type": "channel:rightsignature"
}
